pebble_helpers/__init__.py
pebble_helpers/views/__init__.py
pebble_helpers/views/mixins/__init__.py
pebble_helpers/views/mixins/auth.py
pebble_helpers/views/mixins/form.py
pebble_helpers/views/mixins/time.py
pebble_view_helpers-0.1.0.dist-info/DESCRIPTION.rst
pebble_view_helpers-0.1.0.dist-info/METADATA
pebble_view_helpers-0.1.0.dist-info/RECORD
pebble_view_helpers-0.1.0.dist-info/WHEEL
pebble_view_helpers-0.1.0.dist-info/metadata.json
pebble_view_helpers-0.1.0.dist-info/top_level.txt
